blog_hj3415/.DS_Store
blog_hj3415/__init__.py
blog_hj3415/admin.py
blog_hj3415/apps.py
blog_hj3415/forms.py
blog_hj3415/managers.py
blog_hj3415/models.py
blog_hj3415/views.py
blog_hj3415/migrations/0001_initial.py
blog_hj3415/migrations/0002_portfoliocategory_portfolio.py
blog_hj3415/migrations/__init__.py
blog_hj3415/static/admin/css/markdown_fix.css
blog_hj3415/templates/blog_hj3415/_sidebar_proxy.html
blog_hj3415/templatetags/__init__.py
blog_hj3415/templatetags/blog_pagination.py
blog_hj3415/templatetags/blog_sidebar_tags.py
blog_hj3415/templatetags/blog_utils.py
blog_hj3415-0.3.0.dist-info/WHEEL
blog_hj3415-0.3.0.dist-info/METADATA
blog_hj3415-0.3.0.dist-info/RECORD
