Metadata-Version: 2.4
Name: blog-hj3415
Version: 0.3.0
Summary: blog-hj3415 is the program for blogging
Author-email: Hyungjin Kim <hj3415@gmail.com>
Classifier: License :: OSI Approved :: MIT License
Requires-Dist: django
Requires-Dist: django-markdownx
Requires-Dist: beautifulsoup4
Requires-Dist: lxml
Requires-Dist: pillow
Project-URL: Home, https://www.hyungjin.kr
